sidas_ecs_coordinator/__init__.py
sidas_ecs_coordinator/config.py
sidas_ecs_coordinator/coordinator.py
sidas_ecs_coordinator/py.typed
sidas_ecs_coordinator-0.1.2.dist-info/METADATA
sidas_ecs_coordinator-0.1.2.dist-info/WHEEL
sidas_ecs_coordinator-0.1.2.dist-info/RECORD
