Metadata-Version: 2.4
Name: sidas-ecs-coordinator
Version: 0.1.2
Summary: Add your description here
Author-email: Christian Kranemann <cpkranemann@gmail.com>
Requires-Python: >=3.13
Requires-Dist: sidas>=0.2.11
